agent_lobbi-1.0.1.dist-info/licenses/LICENSE
api/enhanced_a2a_api_bridge.py
api/lobby_api_bridge.py
api/metrics_api.py
core/__init__.py
core/agent_learning.py
core/agent_metrics_enhanced.py
core/agent_metrics_tracker.py
core/analytics.py
core/capability_matcher.py
core/collaboration_engine.py
core/config.py
core/data_bus_orchestrator.py
core/database.py
core/database_setup.py
core/enhanced_lobby_integration.py
core/fast_databus.py
core/fast_message_delivery.py
core/flexible_data_processor.py
core/interaction_tracker.py
core/learning.py
core/load_balancer.py
core/lobby.py
core/lobby_api_fix.py
core/message.py
core/monitoring.py
core/naa_performance_optimized.py
core/neuromorphic_agent_architecture.py
core/postgresql_audit.py
core/redis_database.py
core/security.py
core/security_validator.py
core/world_state.py
mcp/__init__.py
mcp/mcp_agent_manager.py
mcp/mcp_server_factory.py
mcp/mcp_tools.py
persistence/advanced_context_manager.py
persistence/state_context_manager.py
recovery/connection_recovery.py
sdk/__init__.py
sdk/advanced_agent_lobbi_sdk.py
sdk/agent_lobbi_sdk.py
sdk/ecosystem_sdk.py
sdk/enhanced_ecosystem_sdk.py
sdk/monitoring_sdk.py
sdk/website_integrated_sdk.py
sdk/js_sdk/enhanced_ecosystem_sdk.js
sdk/js_sdk/index.js
sdk/js_sdk/package.json
sdk/python_sdk/publish.py
sdk/python_sdk/pyproject.toml
sdk/python_sdk/examples/basic_agent.py
sdk/python_sdk/examples/task_delegation.py
sdk/python_sdk/python_sdk/__init__.py
sdk/python_sdk/python_sdk/cli.py
sdk/python_sdk/python_sdk/client.py
sdk/python_sdk/tests/__init__.py
sdk/python_sdk/tests/test_client.py
security/consensus_system.py
security/data_protection_layer.py
security/game_theory_security.py
security/security_hardening.py
security/task_encryption.py
test_agents/financial_agent.py
test_agents/writer_agent.py
tracking/agent_tracking_system.py
agent_lobbi-1.0.1.dist-info/METADATA
agent_lobbi-1.0.1.dist-info/WHEEL
agent_lobbi-1.0.1.dist-info/entry_points.txt
agent_lobbi-1.0.1.dist-info/top_level.txt
agent_lobbi-1.0.1.dist-info/RECORD
