Metadata-Version: 2.4
Name: agent-lobbi
Version: 1.0.1
Summary: Enhanced A2A+ Agent Collaboration Platform with Advanced Metrics and Neuromorphic Intelligence
Home-page: https://github.com/agentlobby/agent-lobbi
Download-URL: https://github.com/agentlobby/agent-lobbi/archive/v1.0.1.tar.gz
Author: Agent Lobby Team
Author-email: Agent Lobby Team <support@agentlobby.com>
Maintainer: Agent Lobby Team
Maintainer-email: Agent Lobby Team <maintainers@agentlobby.com>
License: MIT
Project-URL: Homepage, https://agentlobby.com
Project-URL: Documentation, https://docs.agentlobby.com
Project-URL: Repository, https://github.com/agentlobby/agent-lobbi
Project-URL: Bug Tracker, https://github.com/agentlobby/agent-lobbi/issues
Project-URL: Changelog, https://github.com/agentlobby/agent-lobbi/blob/main/CHANGELOG.md
Project-URL: Discord, https://discord.gg/agentlobby
Project-URL: Twitter, https://twitter.com/agentlobby
Keywords: agent,collaboration,a2a,artificial intelligence,multi-agent systems,distributed computing,neuromorphic,metrics,analytics,websocket,asyncio,real-time,business intelligence
Platform: any
Classifier: Development Status :: 5 - Production/Stable
Classifier: Intended Audience :: Developers
Classifier: Intended Audience :: Information Technology
Classifier: License :: OSI Approved :: MIT License
Classifier: Operating System :: OS Independent
Classifier: Programming Language :: Python :: 3
Classifier: Programming Language :: Python :: 3.8
Classifier: Programming Language :: Python :: 3.9
Classifier: Programming Language :: Python :: 3.10
Classifier: Programming Language :: Python :: 3.11
Classifier: Programming Language :: Python :: 3.12
Classifier: Topic :: Software Development :: Libraries :: Python Modules
Classifier: Topic :: Internet :: WWW/HTTP :: HTTP Servers
Classifier: Topic :: Scientific/Engineering :: Artificial Intelligence
Classifier: Topic :: System :: Distributed Computing
Classifier: Topic :: System :: Networking
Classifier: Framework :: AsyncIO
Classifier: Environment :: Web Environment
Classifier: Typing :: Typed
Requires-Python: >=3.8
License-File: LICENSE
Requires-Dist: aiohttp>=3.8.0
Requires-Dist: asyncio-mqtt>=0.13.0
Requires-Dist: websockets>=11.0.0
Requires-Dist: pydantic>=2.0.0
Requires-Dist: fastapi>=0.100.0
Requires-Dist: uvicorn>=0.23.0
Requires-Dist: sqlalchemy>=2.0.0
Requires-Dist: alembic>=1.11.0
Requires-Dist: structlog>=23.0.0
Requires-Dist: click>=8.0.0
Requires-Dist: python-multipart>=0.0.6
Requires-Dist: jinja2>=3.1.0
Requires-Dist: cryptography>=41.0.0
Requires-Dist: python-jose[cryptography]>=3.3.0
Requires-Dist: bcrypt>=4.0.0
Requires-Dist: httpx>=0.24.0
Requires-Dist: rich>=13.0.0
Requires-Dist: typer>=0.9.0
Provides-Extra: dev
Requires-Dist: pytest>=7.0.0; extra == "dev"
Requires-Dist: pytest-asyncio>=0.21.0; extra == "dev"
Requires-Dist: pytest-cov>=4.0.0; extra == "dev"
Requires-Dist: black>=22.0.0; extra == "dev"
Requires-Dist: flake8>=4.0.0; extra == "dev"
Requires-Dist: mypy>=0.991; extra == "dev"
Requires-Dist: pre-commit>=2.20.0; extra == "dev"
Requires-Dist: isort>=5.12.0; extra == "dev"
Requires-Dist: bandit>=1.7.0; extra == "dev"
Provides-Extra: docs
Requires-Dist: sphinx>=5.0.0; extra == "docs"
Requires-Dist: sphinx-rtd-theme>=1.0.0; extra == "docs"
Requires-Dist: myst-parser>=0.18.0; extra == "docs"
Requires-Dist: sphinx-autodoc-typehints>=1.19.0; extra == "docs"
Provides-Extra: monitoring
Requires-Dist: prometheus-client>=0.15.0; extra == "monitoring"
Requires-Dist: grafana-client>=3.0.0; extra == "monitoring"
Requires-Dist: statsd>=4.0.0; extra == "monitoring"
Provides-Extra: enterprise
Requires-Dist: redis>=4.0.0; extra == "enterprise"
Requires-Dist: celery>=5.0.0; extra == "enterprise"
Requires-Dist: kubernetes>=24.0.0; extra == "enterprise"
Requires-Dist: psycopg2-binary>=2.9.0; extra == "enterprise"
Provides-Extra: all
Requires-Dist: agent-lobbi[dev,docs,enterprise,monitoring]; extra == "all"
Dynamic: author
Dynamic: download-url
Dynamic: home-page
Dynamic: license-file
Dynamic: maintainer
Dynamic: platform
Dynamic: requires-python
